ccaaws/__init__.py
ccaaws/acm.py
ccaaws/botosession.py
ccaaws/cfnclient.py
ccaaws/cwclient.py
ccaaws/dynamo.py
ccaaws/ec2.py
ccaaws/iamclient.py
ccaaws/paramstore.py
ccaaws/s3filesystem.py
ccaaws-0.4.8.dist-info/WHEEL
ccaaws-0.4.8.dist-info/METADATA
ccaaws-0.4.8.dist-info/RECORD
