Metadata-Version: 2.1
Name: ccaaws
Version: 0.4.8
Summary: AWS boto3 objects for python
Author: ccdale
Author-email: chris.charles.allison+ccaaws@gmail.com
Requires-Python: >=3.6,<4.0
Classifier: Programming Language :: Python :: 3
Classifier: Programming Language :: Python :: 3.6
Classifier: Programming Language :: Python :: 3.7
Classifier: Programming Language :: Python :: 3.8
Classifier: Programming Language :: Python :: 3.9
Requires-Dist: boto3 (>=1.11.5,<2.0.0)
Requires-Dist: ccalogging (>=0.3.3,<0.4.0)
Requires-Dist: ccautils (>=0.4.0,<0.5.0)
